Workbook

Sheet Lead Database
A1: Lead ID | B1: Full Name | C1: Salon Name | D1: City | E1: State | F1: Platform Found | G1: Instagram Handle | H1: Email | I1: Phone | J1: Website | K1: Follower Count | L1: Running Ads? | M1: Lead Score | N1: Lead Tier | O1: Current Phase | P1: First Contact Date | Q1: First Contact Channel | R1: First Response Date | S1: Response Status | T1: Follow-Up Count | U1: Last Follow-Up Date | V1: Landing Page Click? | W1: Purchased? | X1: Purchase Date | Y1: Notes
A2: L001 | B2: Maria Rodriguez | C2: Glow Beauty Salon | D2: Miami | E2: FL | F2: Instagram | G2: @glowbeautymiami | H2: maria@glowbeauty.com | I2: 305-555-0123 | J2: glowbeautysalon.com | K2: 3200 | L2: Yes | M2: 75 | N2: HOT | O2: Attention | P2: 2026-04-01 | Q2: Instagram DM | R2: 2026-04-02 | S2: Replied - Interested | T2: 2 | U2: 2026-04-05 | V2: Yes | W2: No | Y2: Very interested, asked about reactivation module
A3: L002 | B3: Jennifer Kim | C3: JK Hair Studio | D3: Los Angeles | E3: CA | F3: Apollo.io | G3: @jkhairstudio | H3: jen@jkhairstudio.com | I3: 310-555-0456 | J3: jkhairstudio.com | K3: 5600 | L3: Yes | M3: 55 | N3: WARM | O3: Interest | P3: 2026-04-01 | Q3: Cold Email | R3: 2026-04-04 | S3: Replied - Maybe | T3: 1 | U3: 2026-04-04 | V3: No | W3: No | Y3: Opened email 1 and 2, replied asking for more info
A4: L003 | B4: Tasha Williams | C4: Crown & Glory | D4: Atlanta | E4: GA | F4: Facebook Group | G4: @crownandgloryatl | H4: tasha@crownandglory.com | I4: 404-555-0789 | J4: crownandglorysalon.com | K4: 1800 | L4: Unknown | M4: 35 | N4: COOL | O4: Attention | P4: 2026-04-03 | Q4: Facebook DM | S4: No Response | T4: 1 | U4: 2026-04-07 | V4: No | W4: No | Y4: Engaged with FB group post but no DM reply
A5: L004 | B5: Fatima Hassan | C5: Luxe Locks Salon | D5: Houston | E5: TX | F5: Google Maps | G5: @luxelockshtx | H5: fatima@luxelocks.com | I5: 713-555-0321 | J5: luxelockssalon.com | K5: 7800 | L5: Yes | M5: 85 | N5: HOT | O5: Desire | P5: 2026-04-01 | Q5: Instagram DM | R5: 2026-04-01 | S5: Clicked Link | T5: 3 | U5: 2026-04-10 | V5: Yes | W5: No | Y5: Clicked link twice, sent WhatsApp voice note
A6: L005 | B6: David Chen | C6: Studio 88 Hair | D6: San Francisco | E6: CA | F6: LinkedIn | H6: david@studio88hair.com | I6: 415-555-0654 | J6: studio88hair.com | K6: 2100 | L6: No | M6: 25 | N6: COOL | O6: Attention | P6: 2026-04-05 | Q6: LinkedIn | S6: No Response | T6: 0 | V6: No | W6: No | Y6: Connected on LinkedIn, no reply to message

Sheet Daily Activity Log
A1: Date | B1: Day | C1: Week # | D1: Phase | E1: IG DMs Sent | F1: IG DM Replies | G1: DM Reply Rate | H1: Emails Sent (GHL) | I1: Email Opens | J1: Email Open Rate | K1: Email Replies | L1: Email Click-Throughs | M1: LinkedIn Requests | N1: LinkedIn Accepted | O1: LinkedIn Messages | P1: LinkedIn Replies | Q1: FB Group Comments | R1: FB Group Posts | S1: WhatsApp Sent | T1: WhatsApp Replies | U1: Landing Page Visits | V1: Sales | W1: Revenue | X1: Notes
A2: 2026-04-06 | B2: Monday | C2: 1 | D2: Attention | G2: =IF(E2=0,"",F2/E2) | J2: =IF(H2=0,"",I2/H2) | W2: =V2*97
A3: 2026-04-07 | B3: Tuesday | C3: 1 | D3: Attention | G3: =IF(E3=0,"",F3/E3) | J3: =IF(H3=0,"",I3/H3) | W3: =V3*97
A4: 2026-04-08 | B4: Wednesday | C4: 1 | D4: Attention | G4: =IF(E4=0,"",F4/E4) | J4: =IF(H4=0,"",I4/H4) | W4: =V4*97
A5: 2026-04-09 | B5: Thursday | C5: 1 | D5: Attention | G5: =IF(E5=0,"",F5/E5) | J5: =IF(H5=0,"",I5/H5) | W5: =V5*97
A6: 2026-04-10 | B6: Friday | C6: 1 | D6: Attention | G6: =IF(E6=0,"",F6/E6) | J6: =IF(H6=0,"",I6/H6) | W6: =V6*97
A7: 2026-04-11 | B7: Saturday | C7: 1 | D7: Attention | G7: =IF(E7=0,"",F7/E7) | J7: =IF(H7=0,"",I7/H7) | W7: =V7*97
A8: 2026-04-12 | B8: Sunday | C8: 1 | D8: Attention | G8: =IF(E8=0,"",F8/E8) | J8: =IF(H8=0,"",I8/H8) | W8: =V8*97
A9: 2026-04-13 | B9: Monday | C9: 2 | D9: Attention | G9: =IF(E9=0,"",F9/E9) | J9: =IF(H9=0,"",I9/H9) | W9: =V9*97
A10: 2026-04-14 | B10: Tuesday | C10: 2 | D10: Attention | G10: =IF(E10=0,"",F10/E10) | J10: =IF(H10=0,"",I10/H10) | W10: =V10*97
A11: 2026-04-15 | B11: Wednesday | C11: 2 | D11: Attention | G11: =IF(E11=0,"",F11/E11) | J11: =IF(H11=0,"",I11/H11) | W11: =V11*97
A12: 2026-04-16 | B12: Thursday | C12: 2 | D12: Attention | G12: =IF(E12=0,"",F12/E12) | J12: =IF(H12=0,"",I12/H12) | W12: =V12*97
A13: 2026-04-17 | B13: Friday | C13: 2 | D13: Attention | G13: =IF(E13=0,"",F13/E13) | J13: =IF(H13=0,"",I13/H13) | W13: =V13*97
... A43: 2026-05-17 | B43: Sunday | C43: 6 | D43: Action | G43: =IF(E43=0,"",F43/E43) | J43: =IF(H43=0,"",I43/H43) | W43: =V43*97
A44: TOTALS | E44: =SUM(E2:E43) | F44: =SUM(F2:F43) | G44: =IF(E44=0,"",F44/E44) | H44: =SUM(H2:H43) | I44: =SUM(I2:I43) | J44: =IF(H44=0,"",I44/H44) | K44: =SUM(K2:K43) | L44: =SUM(L2:L43) | M44: =SUM(M2:M43) | N44: =SUM(N2:N43) | O44: =SUM(O2:O43) | P44: =SUM(P2:P43) | Q44: =SUM(Q2:Q43) | R44: =SUM(R2:R43) | ... W44: =SUM(W2:W43)

Sheet Weekly Dashboard
A1: Week # | B1: Phase | C1: Total DMs Sent | D1: Total DM Replies | E1: DM Reply Rate | F1: Total Emails Sent | G1: Total Email Opens | H1: Email Open Rate | I1: Total LinkedIn Outreach | J1: LinkedIn Accept Rate | K1: Total LP Visits | L1: Total Sales | M1: Total Revenue | N1: Conversion Rate | O1: Notes
A2: 1 | B2: Attention | C2: =SUM('Daily Activity Log'!E2:E8) | D2: =SUM('Daily Activity Log'!F2:F8) | E2: =IF(C2=0,"",D2/C2) | F2: =SUM('Daily Activity Log'!H2:H8) | G2: =SUM('Daily Activity Log'!I2:I8) | H2: =IF(F2=0,"",G2/F2) | I2: =SUM('Daily Activity Log'!M2:M8) | J2: =IF(I2=0,"",SUM('Daily Activity Log'!N2:N8)/I2) | K2: =SUM('Daily Activity Log'!U2:U8) | L2: =SUM('Daily Activity Log'!V2:V8) | M2: =L2*97 | N2: =IF(K2=0,"",L2/K2)
A3: 2 | B3: Attention | C3: =SUM('Daily Activity Log'!E9:E15) | D3: =SUM('Daily Activity Log'!F9:F15) | E3: =IF(C3=0,"",D3/C3) | F3: =SUM('Daily Activity Log'!H9:H15) | G3: =SUM('Daily Activity Log'!I9:I15) | H3: =IF(F3=0,"",G3/F3) | I3: =SUM('Daily Activity Log'!M9:M15) | J3: =IF(I3=0,"",SUM('Daily Activity Log'!N9:N15)/I3) | K3: =SUM('Daily Activity Log'!U9:U15) | L3: =SUM('Daily Activity Log'!V9:V15) | M3: =L3*97 | N3: =IF(K3=0,"",L3/K3)
A4: 3 | B4: Interest | C4: =SUM('Daily Activity Log'!E16:E22) | D4: =SUM('Daily Activity Log'!F16:F22) | E4: =IF(C4=0,"",D4/C4) | F4: =SUM('Daily Activity Log'!H16:H22) | G4: =SUM('Daily Activity Log'!I16:I22) | H4: =IF(F4=0,"",G4/F4) | I4: =SUM('Daily Activity Log'!M16:M22) | J4: =IF(I4=0,"",SUM('Daily Activity Log'!N16:N22)/I4) | K4: =SUM('Daily Activity Log'!U16:U22) | L4: =SUM('Daily Activity Log'!V16:V22) | M4: =L4*97 | N4: =IF(K4=0,"",L4/K4)
A5: 4 | B5: Interest | C5: =SUM('Daily Activity Log'!E23:E29) | D5: =SUM('Daily Activity Log'!F23:F29) | E5: =IF(C5=0,"",D5/C5) | F5: =SUM('Daily Activity Log'!H23:H29) | G5: =SUM('Daily Activity Log'!I23:I29) | H5: =IF(F5=0,"",G5/F5) | I5: =SUM('Daily Activity Log'!M23:M29) | J5: =IF(I5=0,"",SUM('Daily Activity Log'!N23:N29)/I5) | K5: =SUM('Daily Activity Log'!U23:U29) | L5: =SUM('Daily Activity Log'!V23:V29) | M5: =L5*97 | N5: =IF(K5=0,"",L5/K5)
A6: 5 | B6: Desire | C6: =SUM('Daily Activity Log'!E30:E36) | D6: =SUM('Daily Activity Log'!F30:F36) | E6: =IF(C6=0,"",D6/C6) | F6: =SUM('Daily Activity Log'!H30:H36) | G6: =SUM('Daily Activity Log'!I30:I36) | H6: =IF(F6=0,"",G6/F6) | I6: =SUM('Daily Activity Log'!M30:M36) | J6: =IF(I6=0,"",SUM('Daily Activity Log'!N30:N36)/I6) | K6: =SUM('Daily Activity Log'!U30:U36) | L6: =SUM('Daily Activity Log'!V30:V36) | M6: =L6*97 | N6: =IF(K6=0,"",L6/K6)
A7: 6 | B7: Action | C7: =SUM('Daily Activity Log'!E37:E43) | D7: =SUM('Daily Activity Log'!F37:F43) | E7: =IF(C7=0,"",D7/C7) | F7: =SUM('Daily Activity Log'!H37:H43) | G7: =SUM('Daily Activity Log'!I37:I43) | H7: =IF(F7=0,"",G7/F7) | I7: =SUM('Daily Activity Log'!M37:M43) | J7: =IF(I7=0,"",SUM('Daily Activity Log'!N37:N43)/I7) | K7: =SUM('Daily Activity Log'!U37:U43) | L7: =SUM('Daily Activity Log'!V37:V43) | M7: =L7*97 | N7: =IF(K7=0,"",L7/K7)
A8: GRAND TOTAL | C8: =SUM(C2:C7) | D8: =SUM(D2:D7) | E8: =IF(C8=0,"",D8/C8) | F8: =SUM(F2:F7) | G8: =SUM(G2:G7) | H8: =IF(F8=0,"",G8/F8) | I8: =SUM(I2:I7) | K8: =SUM(K2:K7) | L8: =SUM(L2:L7) | M8: =L8*97 | N8: =IF(K8=0,"",L8/K8)

Sheet Email Sequence Tracker
A1: Email # | B1: Email Name | C1: Phase | D1: Subject Line A | E1: Subject Line B | F1: Send Date | G1: Total Sent | H1: Opens (A) | I1: Open Rate (A) | J1: Opens (B) | K1: Open Rate (B) | L1: Winner | M1: Total Clicks | N1: CTR | O1: Unsubscribes | P1: Replies | Q1: Sales Attributed | R1: Notes
A2: 1 | B2: The Pain | C2: Interest | D2: Are you renting clients or building a business? | E2: The $48,000 mistake most salon owners make every year | I2: =IF(G2=0,"",H2/(G2/2)) | K2: =IF(G2=0,"",J2/(G2/2)) | N2: =IF(G2=0,"",M2/G2)
A3: 2 | B3: Social Proof | C3: Interest | D3: 23 clients came back. Zero ad spend. | E3: How Fatima stopped paying $4,000/month for ads | I3: =IF(G3=0,"",H3/(G3/2)) | K3: =IF(G3=0,"",J3/(G3/2)) | N3: =IF(G3=0,"",M3/G3)
A4: 3 | B4: The Tease | C4: Interest | D4: The 8-module system that filled 500+ salon calendars | E4: Before I show you the price — here's what's inside | I4: =IF(G4=0,"",H4/(G4/2)) | K4: =IF(G4=0,"",J4/(G4/2)) | N4: =IF(G4=0,"",M4/G4)
A5: 4 | B5: Offer Reveal | C5: Desire | D5: Here's everything you get — and the price drops today | E5: $1,041 in value. $97 today. | I5: =IF(G5=0,"",H5/(G5/2)) | K5: =IF(G5=0,"",J5/(G5/2)) | N5: =IF(G5=0,"",M5/G5)
A6: 5 | B6: Bonus Stack | C6: Desire | D6: Here's what you lose if you wait | E6: The bonuses disappear before the price goes up | I6: =IF(G6=0,"",H6/(G6/2)) | K6: =IF(G6=0,"",J6/(G6/2)) | N6: =IF(G6=0,"",M6/G6)
A7: 6 | B7: Testimonials | C7: Desire | D7: Real salon owners. Real numbers. | E7: From $4,000/month in ads to $0 — their stories | I7: =IF(G7=0,"",H7/(G7/2)) | K7: =IF(G7=0,"",J7/(G7/2)) | N7: =IF(G7=0,"",M7/G7)
A8: 7 | B8: 48hr Warning | C8: Action | D8: 48 hours left — then the price goes back to $497 | E8: The math on waiting vs. enrolling right now | I8: =IF(G8=0,"",H8/(G8/2)) | K8: =IF(G8=0,"",J8/(G8/2)) | N8: =IF(G8=0,"",M8/G8)
A9: 8 | B9: 24hr Warning | C9: Action | D9: Last chance — 24 hours before the price changes | E9: What if it doesn't work? (Read this guarantee) | I9: =IF(G9=0,"",H9/(G9/2)) | K9: =IF(G9=0,"",J9/(G9/2)) | N9: =IF(G9=0,"",M9/G9)
A10: 9 | B10: Final Close | C10: Action | D10: This is it — closing in 6 hours [FINAL NOTICE] | E10: Final email. Then it's done. | I10: =IF(G10=0,"",H10/(G10/2)) | K10: =IF(G10=0,"",J10/(G10/2)) | N10: =IF(G10=0,"",M10/G10)

Sheet Channel Performance
A1: Channel | B1: Total Outreach | C1: Total Responses | D1: Response Rate | E1: LP Clicks | F1: Click Rate | G1: Sales | H1: Conversion Rate | I1: Revenue | J1: Time (hrs) | K1: Revenue/Hour | L1: Priority | M1: Notes
A2: Instagram DM | D2: =IF(B2=0,"",C2/B2) | F2: =IF(B2=0,"",E2/B2) | H2: =IF(E2=0,"",G2/E2) | I2: =G2*97 | K2: =IF(J2=0,"",I2/J2)
A3: Cold Email (GHL) | D3: =IF(B3=0,"",C3/B3) | F3: =IF(B3=0,"",E3/B3) | H3: =IF(E3=0,"",G3/E3) | I3: =G3*97 | K3: =IF(J3=0,"",I3/J3)
A4: LinkedIn | D4: =IF(B4=0,"",C4/B4) | F4: =IF(B4=0,"",E4/B4) | H4: =IF(E4=0,"",G4/E4) | I4: =G4*97 | K4: =IF(J4=0,"",I4/J4)
A5: Facebook Groups | D5: =IF(B5=0,"",C5/B5) | F5: =IF(B5=0,"",E5/B5) | H5: =IF(E5=0,"",G5/E5) | I5: =G5*97 | K5: =IF(J5=0,"",I5/J5)
A6: WhatsApp | D6: =IF(B6=0,"",C6/B6) | F6: =IF(B6=0,"",E6/B6) | H6: =IF(E6=0,"",G6/E6) | I6: =G6*97 | K6: =IF(J6=0,"",I6/J6)
A7: Threads | D7: =IF(B7=0,"",C7/B7) | F7: =IF(B7=0,"",E7/B7) | H7: =IF(E7=0,"",G7/E7) | I7: =G7*97 | K7: =IF(J7=0,"",I7/J7)
A8: TOTAL | B8: =SUM(B2:B7) | C8: =SUM(C2:C7) | E8: =SUM(E2:E7) | G8: =SUM(G2:G7) | I8: =SUM(I2:I7) | J8: =SUM(J2:J7)

Sheet 6-Week Execution Calendar
A1: Date | B1: Day | C1: Week # | D1: Phase | E1: Morning (9-11 AM) | F1: Midday (11 AM-1 PM) | G1: Afternoon (2-4 PM) | H1: Evening (4-6 PM) | I1: Key Deliverable | J1: Status
A2: 2026-04-06 | B2: Monday | C2: 1 | D2: Attention | E2: Set up GHL sub-account, configure pipeline stages and tags | F2: Set up Apollo.io, save search filters, start building email list | G2: Join 8 Facebook groups, optimize Instagram bio + link | H2: Prepare first 3 Instagram DM script variants | I2: All platforms set up and configured | J2: Not Started
A3: 2026-04-07 | B3: Tuesday | C3: 1 | D3: Attention | E3: Warm email domain (start process), install G Maps Extractor | F3: Scrape first 2 cities: Miami + LA (Google Maps) | G3: Start Apollo.io list build (target: 200 contacts today) | H3: Verify scraped data, clean email list | I3: 200+ leads scraped and verified | J3: Not Started
A4: 2026-04-08 | B4: Wednesday | C4: 1 | D4: Attention | E4: Send first batch of Instagram DMs (30 DMs) | F4: Continue Apollo.io list build (target: 300 more) | G4: Scrape 2 more cities: Houston + NYC | H4: Comment on 5+ posts in Facebook groups | I4: 30 DMs sent, 500 leads total | J4: Not Started
A5: 2026-04-09 | B5: Thursday | C5: 1 | D5: Attention | E5: Instagram DMs (40 DMs), track responses | F5: Load first email batch into GHL (do NOT send yet) | G5: Scrape 2 more cities: Chicago + Dallas | H5: Continue Facebook group commenting | I5: 40 DMs sent, 700+ leads | J5: Not Started
A6: 2026-04-10 | B6: Friday | C6: 1 | D6: Attention | E6: Instagram DMs (50 DMs), review reply rate | F6: Finalize email list in GHL (500+ contacts) | G6: Scrape 2 more cities: Atlanta + Tampa | H6: Review Week 1 progress, adjust scripts if needed | I6: 50 DMs sent, 1000+ leads in database | J6: Not Started
A7: 2026-04-11 | B7: Saturday | C7: 1 | D7: Attention | E7: Light DM follow-ups to replies | F7: Organize and clean all lead data | G7: Content planning for next week | H7: Rest / review metrics | I7: Database organized | J7: Not Started
A8: 2026-04-12 | B8: Sunday | C8: 1 | D8: Attention | E8: Plan Week 2 priorities | F8: Review DM reply rate and best-performing opener | G8: Prep email sequences in GHL for Week 2 launch | H8: Rest | I8: Week 2 plan ready | J8: Not Started
A9: 2026-04-13 | B9: Monday | C9: 2 | D9: Attention | E9: Instagram DMs (50/day), A/B test openers | F9: Launch first cold email batch in GHL (150/day) | G9: Start LinkedIn outreach (20 requests/day) | H9: First organic Facebook group post | I9: Email + DM + LinkedIn all active | J9: Not Started
A10: 2026-04-14 | B10: Tuesday | C10: 2 | D10: Attention | E10: Instagram DMs (50/day), track responses | F10: Monitor email open rates, adjust subject lines | G10: LinkedIn connection follow-ups | H10: Facebook group commenting | I10: All channels running | J10: Not Started
A11: 2026-04-15 | B11: Wednesday | C11: 2 | D11: Attention | E11: Instagram DMs (40/day) + reply to responses | F11: Cold emails (150/day), review A/B results | G11: LinkedIn messages to new connections | H11: Second Facebook group post | I11: Mid-week metric review | J11: Not Started
A12: 2026-04-16 | B12: Thursday | C12: 2 | D12: Attention | E12: Instagram DMs (40/day) | F12: Cold emails (200/day) — double down on winning subject line | G12: LinkedIn outreach (25/day) | H12: Facebook group commenting + engagement | I12: 200+ emails/day milestone | J12: Not Started
A13: 2026-04-17 | B13: Friday | C13: 2 | D13: Attention | E13: Instagram DMs (40/day) + nurture warm leads | F13: Review email metrics: opens, clicks, replies | G13: LinkedIn (20/day) | H13: WEEKLY REVIEW: DM rate, email rate, LP visits | I13: Weekly KPI review complete | J13: Not Started
... A41: 2026-05-15 | B41: Friday | C41: 6 | D41: Action | E41: Complete campaign post-mortem | F41: Update Channel Performance sheet | G41: Identify top-performing channels for next campaign | H41: Plan next steps / repeat campaign | I41: Campaign complete | J41: Not Started
A42: 2026-05-16 | B42: Saturday | C42: 6 | D42: Action | E42: Rest + celebrate results | J42: Not Started
A43: 2026-05-17 | B43: Sunday | C43: 6 | D43: Action | J43: Not Started
